src/excel.py
src/main.py
pyxl_cli-0.2.1.dist-info/entry_points.txt
pyxl_cli-0.2.1.dist-info/WHEEL
pyxl_cli-0.2.1.dist-info/METADATA
pyxl_cli-0.2.1.dist-info/RECORD
